{"stat.mineBlock.minecraft.stonebrick":200,"stat.useItem.minecraft.fence_gate":4,"stat.craftItem.minecraft.iron_helmet":3,"stat.mineBlock.minecraft.emerald_ore":5,"stat.pickup.minecraft.log2":266,"stat.mineBlock.minecraft.netherrack":7,"stat.useItem.minecraft.dark_oak_fence_gate":9,"stat.craftItem.minecraft.carpet":3,"stat.useItem.minecraft.brown_mushroom":23,"stat.useItem.minecraft.netherrack":2,"stat.useItem.minecraft.iron_hoe":15,"stat.mineBlock.minecraft.glass":5,"achievement.acquireIron":29,"stat.craftingTableInteraction":269,"stat.useItem.minecraft.minecart":9,"stat.useItem.minecraft.iron_shovel":1187,"stat.pickup.minecraft.sapling":23,"stat.damageDealt":48196,"stat.useItem.minecraft.fence":85,"stat.craftItem.minecraft.minecart":2,"stat.killEntity.Bat":3,"stat.mineBlock.minecraft.red_mushroom_block":4,"stat.pickup.minecraft.cooked_beef":47,"stat.pickup.minecraft.spider_eye":3,"stat.crouchOneCm":390075,"stat.useItem.minecraft.shears":1,"stat.useItem.minecraft.potato":97,"stat.mineBlock.minecraft.red_mushroom":55,"stat.pickup.minecraft.rotten_flesh":67,"achievement.exploreAllBiomes":{"value":0,"progress":["Roofed Forest M","Extreme Hills+","Desert","Mesa Plateau F","Taiga","Extreme Hills","TaigaHills","Plains","Swampland M","Hell","ForestHills","Forest","DesertHills","Birch Forest","Mesa","Roofed Forest","Savanna","River","Swampland"]},"stat.mineBlock.minecraft.double_plant":86,"stat.craftItem.minecraft.iron_pickaxe":10,"stat.useItem.minecraft.spruce_door":6,"stat.pickup.minecraft.dark_oak_fence_gate":3,"stat.mineBlock.minecraft.yellow_flower":23,"stat.craftItem.minecraft.wool":2,"stat.craftItem.minecraft.bowl":12,"stat.mineBlock.minecraft.golden_rail":2,"stat.pickup.minecraft.golden_rail":1,"stat.breakItem.minecraft.iron_shovel":4,"stat.entityKilledBy.LavaSlime":1,"stat.pickup.minecraft.dirt":1144,"stat.useItem.minecraft.chest":46,"stat.mineBlock.minecraft.furnace":5,"stat.craftItem.minecraft.bed":1,"stat.killEntity.Sheep":11,"stat.mineBlock.minecraft.sand":230,"stat.pickup.minecraft.diamond_helmet":1,"stat.sneakTime":14324,"stat.useItem.minecraft.cobblestone":507,"stat.pickup.minecraft.pumpkin":15,"stat.craftItem.minecraft.cooked_chicken":186,"stat.craftItem.minecraft.emerald_block":1,"stat.pickup.minecraft.wheat":74,"stat.mineBlock.minecraft.sandstone":3,"stat.mineBlock.minecraft.waterlily":4,"stat.craftItem.minecraft.chest":37,"stat.mineBlock.minecraft.redstone_torch":1,"stat.useItem.minecraft.wooden_door":7,"stat.useItem.minecraft.record_cat":1,"achievement.openInventory":1356,"stat.pickup.minecraft.sand":23,"stat.craftItem.minecraft.map":2,"stat.pickup.minecraft.yellow_flower":5,"stat.trappedChestTriggered":4,"stat.killEntity.Cow":23,"stat.pickup.minecraft.stained_hardened_clay":3,"stat.useItem.minecraft.diamond_pickaxe":2390,"stat.craftItem.minecraft.birch_fence_gate":2,"stat.craftItem.minecraft.fence_gate":1,"stat.useItem.minecraft.log":6,"stat.craftItem.minecraft.iron_chestplate":3,"stat.pickup.minecraft.mutton":12,"stat.mineBlock.minecraft.brown_mushroom_block":8,"stat.useItem.minecraft.red_mushroom":31,"stat.useItem.minecraft.diamond_shovel":2844,"stat.useItem.minecraft.snowball":2,"stat.useItem.minecraft.carrot_on_a_stick":4,"stat.entityKilledBy.Guardian":1,"stat.craftItem.minecraft.furnace":8,"stat.craftItem.minecraft.torch":1790,"stat.mineBlock.minecraft.log":634,"stat.breakItem.minecraft.stone_shovel":9,"stat.useItem.minecraft.planks":409,"stat.talkedToVillager":1,"stat.fallOneCm":220280,"stat.pickup.minecraft.iron_ore":6,"achievement.buildFurnace":8,"stat.useItem.minecraft.cooked_chicken":27,"stat.useItem.minecraft.boat":1,"stat.useItem.minecraft.torch":1949,"stat.craftItem.minecraft.shield":1,"stat.craftItem.minecraft.coal":225,"stat.craftItem.minecraft.bread":748,"stat.useItem.minecraft.bed":2,"stat.useItem.minecraft.stone_pickaxe":2048,"stat.pickup.minecraft.diamond_leggings":1,"stat.craftItem.minecraft.cooked_mutton":6,"stat.useItem.minecraft.water_bucket":99,"stat.pickup.minecraft.carrot":134,"stat.craftItem.minecraft.stone_axe":6,"stat.mineBlock.minecraft.clay":8,"stat.pickup.minecraft.minecart":4,"stat.useItem.minecraft.wheat_seeds":2090,"stat.mineBlock.minecraft.gold_ore":22,"stat.mineBlock.minecraft.rail":1,"stat.useItem.minecraft.stonebrick":2343,"achievement.buildWorkBench":16,"stat.useItem.minecraft.stone":51,"stat.useItem.minecraft.furnace":13,"stat.craftItem.minecraft.diamond_sword":1,"stat.craftItem.minecraft.iron_leggings":3,"stat.useItem.minecraft.ladder":165,"stat.pigOneCm":19273,"stat.pickup.minecraft.item_frame":1,"achievement.killCow":12,"stat.useItem.minecraft.potion":1,"stat.mineBlock.minecraft.pumpkin":142,"stat.mineBlock.minecraft.slime":11,"stat.pickup.minecraft.beef":3,"stat.useItem.minecraft.melon":3,"stat.mineBlock.minecraft.vine":3,"achievement.portal":12,"stat.pickup.minecraft.pumpkin_seeds":16,"stat.flyOneCm":533325,"stat.mineBlock.minecraft.chest":11,"achievement.buildPickaxe":23,"stat.mineBlock.minecraft.torch":174,"stat.mineBlock.minecraft.birch_fence":3,"stat.craftItem.minecraft.cooked_beef":117,"stat.mineBlock.minecraft.iron_ore":641,"stat.damageTaken":14249,"stat.pickup.minecraft.coal":24,"stat.pickup.minecraft.string":17,"stat.useItem.minecraft.diamond_sword":828,"stat.useItem.minecraft.wooden_pressure_plate":12,"stat.craftItem.minecraft.wooden_pressure_plate":9,"stat.mineBlock.minecraft.brown_mushroom":43,"stat.pickup.minecraft.shield":1,"stat.useItem.minecraft.oak_stairs":2,"stat.killEntity.Chicken":240,"stat.craftItem.minecraft.stone_pickaxe":15,"stat.mineBlock.minecraft.cobblestone":130,"stat.recordPlayed":3,"stat.craftItem.minecraft.ladder":39,"stat.craftItem.minecraft.wooden_shovel":2,"stat.sleepInBed":3,"stat.useItem.minecraft.stained_hardened_clay":3,"stat.craftItem.minecraft.dark_oak_fence_gate":5,"stat.pickup.minecraft.snowball":2,"stat.useItem.minecraft.golden_rail":2,"stat.useItem.minecraft.dye":33,"stat.pickup.minecraft.diamond_sword":2,"stat.mineBlock.minecraft.wool":2,"stat.breakItem.minecraft.stone_pickaxe":14,"stat.useItem.minecraft.rail":1,"stat.entityKilledBy.Creeper":2,"stat.pickup.minecraft.torch":15,"stat.useItem.minecraft.log2":32,"stat.useItem.minecraft.stone_sword":131,"stat.climbOneCm":595980,"stat.pickup.minecraft.feather":14,"stat.pickup.minecraft.diamond_chestplate":1,"stat.useItem.minecraft.sapling":1,"stat.drop":123,"stat.breakItem.minecraft.diamond_shovel":1,"stat.pickup.minecraft.porkchop":3,"stat.craftItem.minecraft.boat":1,"stat.craftItem.minecraft.iron_hoe":2,"stat.craftItem.minecraft.iron_axe":2,"stat.mineBlock.minecraft.wooden_slab":71,"achievement.makeBread":635,"stat.craftItem.minecraft.mushroom_stew":13,"stat.pickup.minecraft.chicken":11,"stat.useItem.minecraft.stone_slab":321,"stat.mineBlock.minecraft.fence":35,"stat.useItem.minecraft.cooked_porkchop":20,"stat.craftItem.minecraft.oak_stairs":4,"stat.mineBlock.minecraft.melon_block":1,"stat.killEntity.Creeper":12,"stat.mineBlock.minecraft.planks":111,"stat.craftItem.minecraft.stone_slab":312,"stat.leaveGame":64,"stat.craftItem.minecraft.iron_ingot":599,"stat.drop.minecraft.diamond_sword":1,"stat.pickup.minecraft.planks":1,"stat.mineBlock.minecraft.leaves":915,"stat.useItem.minecraft.painting":1,"achievement.buildSword":2,"stat.craftItem.minecraft.pumpkin_seeds":76,"stat.craftItem.minecraft.wooden_door":3,"achievement.mineWood":1198,"stat.mineBlock.minecraft.red_flower":21,"stat.mineBlock.minecraft.stone_slab":50,"stat.useItem.minecraft.iron_axe":10,"stat.craftItem.minecraft.dye":39,"stat.pickup.minecraft.diamond_hoe":1,"stat.pickup.minecraft.magma_cream":1,"stat.craftItem.minecraft.diamond_pickaxe":1,"stat.pickup.minecraft.log":42,"stat.pickup.minecraft.wooden_slab":4,"stat.useItem.minecraft.stone_shovel":1591,"stat.diveOneCm":357381,"stat.craftItem.minecraft.bow":1,"stat.useItem.minecraft.birch_fence_gate":2,"stat.pickup.minecraft.fence_gate":1,"stat.mineBlock.minecraft.dark_oak_fence_gate":5,"stat.useItem.minecraft.bow":294,"stat.useItem.minecraft.cooked_beef":66,"stat.mineBlock.minecraft.crafting_table":6,"stat.mineBlock.minecraft.hardened_clay":16,"stat.pickup.minecraft.bow":7,"stat.pickup.minecraft.diamond_pickaxe":1,"stat.pickup.minecraft.reeds":53,"stat.useItem.minecraft.glass_bottle":1,"stat.mineBlock.minecraft.cactus":9,"achievement.diamonds":1,"stat.useItem.minecraft.egg":859,"stat.craftItem.minecraft.stonebrick":2510,"stat.useItem.minecraft.crafting_table":20,"stat.craftItem.minecraft.paper":258,"stat.pickup.minecraft.apple":2,"stat.useItem.minecraft.stone_hoe":411,"stat.pickup.minecraft.prismarine_shard":2,"stat.mineBlock.minecraft.obsidian":24,"stat.killEntity.Enderman":1,"stat.craftItem.minecraft.painting":1,"stat.pickup.minecraft.slime":3,"stat.breakItem.minecraft.wooden_shovel":2,"stat.useItem.minecraft.glass":30,"stat.mineBlock.minecraft.dark_oak_fence":44,"achievement.buildBetterPickaxe":23,"stat.timeSinceDeath":122631,"stat.craftItem.minecraft.cooked_porkchop":26,"stat.mineBlock.minecraft.leaves2":49,"stat.useItem.minecraft.gravel":8,"stat.boatOneCm":428936,"stat.useItem.minecraft.wool":2,"stat.craftItem.minecraft.bucket":4,"achievement.buildHoe":8,"stat.craftItem.minecraft.iron_shovel":7,"stat.useItem.minecraft.reeds":24,"stat.pickup.minecraft.bucket":1,"stat.pickup.minecraft.stone":14,"stat.useItem.minecraft.sand":21,"achievement.killEnemy":188,"stat.pickup.minecraft.leather_chestplate":1,"stat.mineBlock.minecraft.snow_layer":3,"stat.killEntity.LavaSlime":23,"stat.craftItem.minecraft.fence":81,"stat.pickup.minecraft.poisonous_potato":2,"stat.playOneMinute":3934919,"stat.useItem.minecraft.redstone_torch":1,"stat.craftItem.minecraft.gold_ingot":89,"stat.useItem.minecraft.pumpkin_seeds":103,"stat.killEntity.Pig":7,"stat.pickup.minecraft.wool":8,"stat.killEntity.Spider":25,"stat.craftItem.minecraft.glass":30,"stat.craftItem.minecraft.stone_shovel":10,"stat.animalsBred":236,"stat.pickup.minecraft.dark_oak_fence":4,"stat.craftItem.minecraft.stick":1048,"stat.pickup.minecraft.golden_chestplate":1,"stat.entityKilledBy.Skeleton":1,"stat.useItem.minecraft.fishing_rod":16,"stat.drop.minecraft.bow":3,"stat.furnaceInteraction":435,"stat.pickup.minecraft.iron_shovel":1,"stat.craftItem.minecraft.wooden_slab":828,"stat.craftItem.minecraft.baked_potato":69,"stat.useItem.minecraft.dark_oak_fence":253,"stat.craftItem.minecraft.compass":2,"stat.breakItem.minecraft.stone_hoe":3,"stat.mineBlock.minecraft.coal_ore":1452,"stat.craftItem.minecraft.fishing_rod":1,"stat.useItem.minecraft.bread":213,"stat.mineBlock.minecraft.log2":804,"stat.mineBlock.minecraft.wooden_pressure_plate":4,"stat.entityKilledBy.Zombie":2,"stat.mineBlock.minecraft.tallgrass":2201,"stat.craftItem.minecraft.stone_sword":1,"stat.pickup.minecraft.stone_slab":2,"stat.useItem.minecraft.iron_sword":3,"achievement.breedCow":25,"stat.useItem.minecraft.written_book":4,"stat.useItem.minecraft.stone_axe":970,"stat.craftItem.minecraft.crafting_table":16,"stat.mobKills":482,"stat.mineBlock.minecraft.stone":3752,"stat.mineBlock.minecraft.cobblestone_wall":1,"stat.craftItem.minecraft.diamond_shovel":1,"stat.useItem.minecraft.bucket":99,"stat.killEntity.Zombie":97,"stat.mineBlock.minecraft.dirt":6779,"stat.mineBlock.minecraft.deadbush":5,"stat.useItem.minecraft.sign":41,"stat.minecartOneCm":253462,"stat.mineBlock.minecraft.fence_gate":1,"stat.useItem.minecraft.pumpkin_pie":2,"stat.useItem.minecraft.tallgrass":11,"stat.useItem.minecraft.carrot":92,"stat.craftItem.minecraft.iron_boots":3,"stat.killEntity.Guardian":1,"stat.pickup.minecraft.bone":47,"stat.pickup.minecraft.wheat_seeds":171,"stat.craftItem.minecraft.dark_oak_door":6,"stat.swimOneCm":537883,"stat.useItem.minecraft.dark_oak_door":3,"stat.useItem.minecraft.diamond_axe":1075,"stat.killEntity.Skeleton":28,"stat.walkOneCm":26080556,"stat.pickup.minecraft.arrow":75,"stat.craftItem.minecraft.dark_oak_fence":240,"stat.craftItem.minecraft.stone_hoe":5,"stat.mineBlock.minecraft.lapis_ore":12,"stat.useItem.minecraft.carpet":5,"stat.jump":18697,"stat.mineBlock.minecraft.stained_hardened_clay":11,"stat.craftItem.minecraft.stone":1447,"stat.pickup.minecraft.potato":112,"stat.killEntity.Witch":1,"stat.useItem.minecraft.record_chirp":2,"stat.useItem.minecraft.apple":3,"stat.breakItem.minecraft.iron_pickaxe":9,"stat.mineBlock.minecraft.ladder":3,"stat.craftItem.minecraft.sign":36,"stat.deaths":14,"stat.mineBlock.minecraft.glowstone":40,"stat.useItem.minecraft.wooden_slab":797,"stat.craftItem.minecraft.hardened_clay":1,"stat.mineBlock.minecraft.gravel":84,"stat.useItem.minecraft.baked_potato":10,"stat.craftItem.minecraft.clock":1,"stat.pickup.minecraft.egg":194,"stat.craftItem.minecraft.diamond_hoe":1,"stat.craftItem.minecraft.planks":2022,"stat.mineBlock.minecraft.redstone_ore":35,"stat.chestOpened":1180,"stat.pickup.minecraft.gunpowder":18,"stat.pickup.minecraft.diamond_axe":1,"stat.useItem.minecraft.diamond_hoe":53,"stat.craftItem.minecraft.shears":1,"stat.pickup.minecraft.cobblestone":35,"stat.killEntity.Squid":2,"stat.useItem.minecraft.wooden_shovel":155,"stat.useItem.minecraft.iron_pickaxe":2322,"stat.craftItem.minecraft.sugar":482,"stat.breakItem.minecraft.stone_axe":6,"stat.sprintOneCm":6958840,"stat.useItem.minecraft.dirt":3726,"stat.pickup.minecraft.diamond_boots":1}